{"symbol": "ALLO", "annualReports": [{"fiscalDateEnding": "2024-12-31", "reportedCurrency": "USD", "totalAssets": "548710000", "totalCurrentAssets": "303386000", "cashAndCashEquivalentsAtCarryingValue": "75218000", "cashAndShortTermInvestments": "75218000", "inventory": "None", "currentNetReceivables": "1900000", "totalNonCurrentAssets": "245324000", "propertyPlantEquipment": "None", "accumulatedDepreciationAmortizationPPE": "None", "intangibleAssets": "None", "intangibleAssetsExcludingGoodwill": "None", "goodwill": "None", "investments": "None", "longTermInvestments": "80673000", "shortTermInvestments": "217258000", "otherCurrentAssets": "9010000", "otherNonCurrentAssets": "None", "totalLiabilities": "126531000", "totalCurrentLiabilities": "35523000", "currentAccountsPayable": "5394000", "deferredRevenue": "None", "currentDebt": "None", "shortTermDebt": "7509000", "totalNonCurrentLiabilities": "91008000", "capitalLeaseObligations": "90756000", "longTermDebt": "None", "currentLongTermDebt": "None", "longTermDebtNoncurrent": "None", "shortLongTermDebtTotal": "90756000", "otherCurrentLiabilities": "22620000", "otherNonCurrentLiabilities": "7761000", "totalShareholderEquity": "422179000", "treasuryStock": "None", "retainedEarnings": "-1819823000", "commonStock": "212000", "commonStockSharesOutstanding": "194812000"}, {"fiscalDateEnding": "2023-12-31", "reportedCurrency": "USD", "totalAssets": "642837000", "totalCurrentAssets": "459115000", "cashAndCashEquivalentsAtCarryingValue": "83155000", "cashAndShortTermInvestments": "83155000", "inventory": "-62451000", "currentNetReceivables": "1700000", "totalNonCurrentAssets": "183722000", "propertyPlantEquipment": "None", "accumulatedDepreciationAmortizationPPE": "None", "intangibleAssets": "None", "intangibleAssetsExcludingGoodwill": "None", "goodwill": "None", "investments": "None", "longTermInvestments": "3645000", "shortTermInvestments": "365542000", "otherCurrentAssets": "8718000", "otherNonCurrentAssets": "None", "totalLiabilities": "130604000", "totalCurrentLiabilities": "37079000", "currentAccountsPayable": "5897000", "deferredRevenue": "None", "currentDebt": "None", "shortTermDebt": "6775000", "totalNonCurrentLiabilities": "93525000", "capitalLeaseObligations": "95121000", "longTermDebt": "None", "currentLongTermDebt": "None", "longTermDebtNoncurrent": "None", "shortLongTermDebtTotal": "95121000", "otherCurrentLiabilities": "24321000", "otherNonCurrentLiabilities": "5179000", "totalShareholderEquity": "512233000", "treasuryStock": "None", "retainedEarnings": "-1562233000", "commonStock": "169000", "commonStockSharesOutstanding": "156932000"}, {"fiscalDateEnding": "2022-12-31", "reportedCurrency": "USD", "totalAssets": "821579000", "totalCurrentAssets": "528824000", "cashAndCashEquivalentsAtCarryingValue": "61904000", "cashAndShortTermInvestments": "61904000", "inventory": "-62451000", "currentNetReceivables": "3300000", "totalNonCurrentAssets": "292755000", "propertyPlantEquipment": "196431000", "accumulatedDepreciationAmortizationPPE": "None", "intangibleAssets": "None", "intangibleAssetsExcludingGoodwill": "None", "goodwill": "None", "investments": "None", "longTermInvestments": "71968000", "shortTermInvestments": "455416000", "otherCurrentAssets": "11504000", "otherNonCurrentAssets": "None", "totalLiabilities": "154697000", "totalCurrentLiabilities": "53728000", "currentAccountsPayable": "13890000", "deferredRevenue": "None", "currentDebt": "None", "shortTermDebt": "6002000", "totalNonCurrentLiabilities": "100969000", "capitalLeaseObligations": "101124000", "longTermDebt": "None", "currentLongTermDebt": "None", "longTermDebtNoncurrent": "None", "shortLongTermDebtTotal": "101124000", "otherCurrentLiabilities": "33741000", "otherNonCurrentLiabilities": "1569000", "totalShareholderEquity": "666882000", "treasuryStock": "None", "retainedEarnings": "-1234968000", "commonStock": "144000", "commonStockSharesOutstanding": "143147000"}, {"fiscalDateEnding": "2021-12-31", "reportedCurrency": "USD", "totalAssets": "1050828000", "totalCurrentAssets": "471323000", "cashAndCashEquivalentsAtCarryingValue": "173314000", "cashAndShortTermInvestments": "173314000", "inventory": "-20021000", "currentNetReceivables": "6000000", "totalNonCurrentAssets": "579505000", "propertyPlantEquipment": "122990000", "accumulatedDepreciationAmortizationPPE": "None", "intangibleAssets": "None", "intangibleAssetsExcludingGoodwill": "None", "goodwill": "None", "investments": "None", "longTermInvestments": "352179000", "shortTermInvestments": "283988000", "otherCurrentAssets": "14021000", "otherNonCurrentAssets": "None", "totalLiabilities": "125628000", "totalCurrentLiabilities": "47907000", "currentAccountsPayable": "10255000", "deferredRevenue": "None", "currentDebt": "None", "shortTermDebt": "3200000", "totalNonCurrentLiabilities": "77721000", "capitalLeaseObligations": "69929000", "longTermDebt": "None", "currentLongTermDebt": "None", "longTermDebtNoncurrent": "None", "shortLongTermDebtTotal": "73129000", "otherCurrentLiabilities": "34296000", "otherNonCurrentLiabilities": "74054000", "totalShareholderEquity": "925200000", "treasuryStock": "None", "retainedEarnings": "-894554000", "commonStock": "142000", "commonStockSharesOutstanding": "135820000"}, {"fiscalDateEnding": "2020-12-31", "reportedCurrency": "USD", "totalAssets": "1227829000", "totalCurrentAssets": "845130000", "cashAndCashEquivalentsAtCarryingValue": "183351000", "cashAndShortTermInvestments": "183351000", "inventory": "-207008000", "currentNetReceivables": "2800000", "totalNonCurrentAssets": "382699000", "propertyPlantEquipment": "118840000", "accumulatedDepreciationAmortizationPPE": "None", "intangibleAssets": "None", "intangibleAssetsExcludingGoodwill": "None", "goodwill": "None", "investments": "None", "longTermInvestments": "204208000", "shortTermInvestments": "644559000", "otherCurrentAssets": "17220000", "otherNonCurrentAssets": "None", "totalLiabilities": "148212000", "totalCurrentLiabilities": "94320000", "currentAccountsPayable": "10390000", "deferredRevenue": "None", "currentDebt": "None", "shortTermDebt": "2974000", "totalNonCurrentLiabilities": "53892000", "capitalLeaseObligations": "53783000", "longTermDebt": "None", "currentLongTermDebt": "None", "longTermDebtNoncurrent": "None", "shortLongTermDebtTotal": "53783000", "otherCurrentLiabilities": "41964000", "otherNonCurrentLiabilities": "53892000", "totalShareholderEquity": "1079617000", "treasuryStock": "None", "retainedEarnings": "-646343000", "commonStock": "140000", "commonStockSharesOutstanding": "120370000"}, {"fiscalDateEnding": "2019-12-31", "reportedCurrency": "USD", "totalAssets": "717802000", "totalCurrentAssets": "544576000", "cashAndCashEquivalentsAtCarryingValue": "175126000", "cashAndShortTermInvestments": "175126000", "inventory": "-60725000", "currentNetReceivables": "2403000", "totalNonCurrentAssets": "173226000", "propertyPlantEquipment": "100944000", "accumulatedDepreciationAmortizationPPE": "None", "intangibleAssets": "151000", "intangibleAssetsExcludingGoodwill": "151000", "goodwill": "None", "investments": "None", "longTermInvestments": "63214000", "shortTermInvestments": "355407000", "otherCurrentAssets": "11640000", "otherNonCurrentAssets": "None", "totalLiabilities": "88779000", "totalCurrentLiabilities": "33079000", "currentAccountsPayable": "9250000", "deferredRevenue": "None", "currentDebt": "None", "shortTermDebt": "1679000", "totalNonCurrentLiabilities": "55700000", "capitalLeaseObligations": "51349000", "longTermDebt": "None", "currentLongTermDebt": "None", "longTermDebtNoncurrent": "None", "shortLongTermDebtTotal": "53028000", "otherCurrentLiabilities": "22150000", "otherNonCurrentLiabilities": "4351000", "totalShareholderEquity": "629023000", "treasuryStock": "None", "retainedEarnings": "-396122000", "commonStock": "124000", "commonStockSharesOutstanding": "101061000"}, {"fiscalDateEnding": "2018-12-31", "reportedCurrency": "USD", "totalAssets": "773855000", "totalCurrentAssets": "467982000", "cashAndCashEquivalentsAtCarryingValue": "721350000", "cashAndShortTermInvestments": "721350000", "inventory": "-261966000", "currentNetReceivables": "3108000", "totalNonCurrentAssets": "305873000", "propertyPlantEquipment": "41610000", "accumulatedDepreciationAmortizationPPE": "None", "intangibleAssets": "754000", "intangibleAssetsExcludingGoodwill": "754000", "goodwill": "None", "investments": "None", "longTermInvestments": "261966000", "shortTermInvestments": "366952000", "otherCurrentAssets": "5490000", "otherNonCurrentAssets": "None", "totalLiabilities": "70691000", "totalCurrentLiabilities": "29459000", "currentAccountsPayable": "12338000", "deferredRevenue": "None", "currentDebt": "None", "shortTermDebt": "None", "totalNonCurrentLiabilities": "41232000", "capitalLeaseObligations": "34456000", "longTermDebt": "34456000", "currentLongTermDebt": "None", "longTermDebtNoncurrent": "None", "shortLongTermDebtTotal": "34456000", "otherCurrentLiabilities": "17121000", "otherNonCurrentLiabilities": "6776000", "totalShareholderEquity": "703164000", "treasuryStock": "None", "retainedEarnings": "-211528000", "commonStock": "121000", "commonStockSharesOutstanding": "89690000"}, {"fiscalDateEnding": "2017-12-31", "reportedCurrency": "USD", "totalAssets": "0", "totalCurrentAssets": "0", "cashAndCashEquivalentsAtCarryingValue": "0", "cashAndShortTermInvestments": "0", "inventory": "None", "currentNetReceivables": "None", "totalNonCurrentAssets": "0", "propertyPlantEquipment": "None", "accumulatedDepreciationAmortizationPPE": "None", "intangibleAssets": "None", "intangibleAssetsExcludingGoodwill": "None", "goodwill": "None", "investments": "None", "longTermInvestments": "0", "shortTermInvestments": "0", "otherCurrentAssets": "None", "otherNonCurrentAssets": "None", "totalLiabilities": "2000", "totalCurrentLiabilities": "2000", "currentAccountsPayable": "0", "deferredRevenue": "None", "currentDebt": "None", "shortTermDebt": "None", "totalNonCurrentLiabilities": "0", "capitalLeaseObligations": "None", "longTermDebt": "None", "currentLongTermDebt": "None", "longTermDebtNoncurrent": "None", "shortLongTermDebtTotal": "None", "otherCurrentLiabilities": "2000", "otherNonCurrentLiabilities": "None", "totalShareholderEquity": "-2000", "treasuryStock": "None", "retainedEarnings": "-23000", "commonStock": "26000", "commonStockSharesOutstanding": "44011274"}], "quarterlyReports": [{"fiscalDateEnding": "2025-09-30", "reportedCurrency": "USD", "totalAssets": "439771000", "totalCurrentAssets": "260719000", "cashAndCashEquivalentsAtCarryingValue": "37815000", "cashAndShortTermInvestments": "37815000", "inventory": "None", "currentNetReceivables": "2100000", "totalNonCurrentAssets": "179052000", "propertyPlantEquipment": "None", "accumulatedDepreciationAmortizationPPE": "None", "intangibleAssets": "None", "intangibleAssetsExcludingGoodwill": "None", "goodwill": "None", "investments": "None", "longTermInvestments": "24944000", "shortTermInvestments": "214379000", "otherCurrentAssets": "6425000", "otherNonCurrentAssets": "None", "totalLiabilities": "124442000", "totalCurrentLiabilities": "31833000", "currentAccountsPayable": "3699000", "deferredRevenue": "None", "currentDebt": "None", "shortTermDebt": "8007999", "totalNonCurrentLiabilities": "92609000", "capitalLeaseObligations": "77134000", "longTermDebt": "None", "currentLongTermDebt": "None", "longTermDebtNoncurrent": "None", "shortLongTermDebtTotal": "85142000", "otherCurrentLiabilities": "20126000", "otherNonCurrentLiabilities": "15475000", "totalShareholderEquity": "315329000", "treasuryStock": "None", "retainedEarnings": "-1971899000", "commonStock": "223000", "commonStockSharesOutstanding": "222038680"}, {"fiscalDateEnding": "2025-06-30", "reportedCurrency": "USD", "totalAssets": "470593000", "totalCurrentAssets": "282655000", "cashAndCashEquivalentsAtCarryingValue": "52332000", "cashAndShortTermInvestments": "52332000", "inventory": "None", "currentNetReceivables": "1700000", "totalNonCurrentAssets": "187938000", "propertyPlantEquipment": "None", "accumulatedDepreciationAmortizationPPE": "None", "intangibleAssets": "None", "intangibleAssetsExcludingGoodwill": "None", "goodwill": "None", "investments": "None", "longTermInvestments": "29510000", "shortTermInvestments": "220788000", "otherCurrentAssets": "9535000", "otherNonCurrentAssets": "None", "totalLiabilities": "126032000", "totalCurrentLiabilities": "31675000", "currentAccountsPayable": "4851000", "deferredRevenue": "None", "currentDebt": "None", "shortTermDebt": "7756000", "totalNonCurrentLiabilities": "94357000", "capitalLeaseObligations": "79241000", "longTermDebt": "None", "currentLongTermDebt": "None", "longTermDebtNoncurrent": "None", "shortLongTermDebtTotal": "79241000", "otherCurrentLiabilities": "26824000", "otherNonCurrentLiabilities": "15116000", "totalShareholderEquity": "344561000", "treasuryStock": "None", "retainedEarnings": "-1930499000", "commonStock": "220000", "commonStockSharesOutstanding": "218929548"}, {"fiscalDateEnding": "2025-03-31", "reportedCurrency": "USD", "totalAssets": "507982000", "totalCurrentAssets": "291576000", "cashAndCashEquivalentsAtCarryingValue": "42455000", "cashAndShortTermInvestments": "42455000", "inventory": "None", "currentNetReceivables": "2300000", "totalNonCurrentAssets": "216406000", "propertyPlantEquipment": "None", "accumulatedDepreciationAmortizationPPE": "None", "intangibleAssets": "None", "intangibleAssetsExcludingGoodwill": "None", "goodwill": "None", "investments": "None", "longTermInvestments": "55506000", "shortTermInvestments": "237588000", "otherCurrentAssets": "11533000", "otherNonCurrentAssets": "None", "totalLiabilities": "122589000", "totalCurrentLiabilities": "30022000", "currentAccountsPayable": "5058000", "deferredRevenue": "None", "currentDebt": "None", "shortTermDebt": "7631000", "totalNonCurrentLiabilities": "92567000", "capitalLeaseObligations": "81292000", "longTermDebt": "None", "currentLongTermDebt": "None", "longTermDebtNoncurrent": "None", "shortLongTermDebtTotal": "81292000", "otherCurrentLiabilities": "24964000", "otherNonCurrentLiabilities": "11275000", "totalShareholderEquity": "385393000", "treasuryStock": "None", "retainedEarnings": "-1879556000", "commonStock": "219000", "commonStockSharesOutstanding": "215359000"}, {"fiscalDateEnding": "2024-12-31", "reportedCurrency": "USD", "totalAssets": "548710000", "totalCurrentAssets": "303386000", "cashAndCashEquivalentsAtCarryingValue": "75218000", "cashAndShortTermInvestments": "75218000", "inventory": "None", "currentNetReceivables": "1900000", "totalNonCurrentAssets": "245324000", "propertyPlantEquipment": "None", "accumulatedDepreciationAmortizationPPE": "None", "intangibleAssets": "None", "intangibleAssetsExcludingGoodwill": "None", "goodwill": "None", "investments": "None", "longTermInvestments": "80673000", "shortTermInvestments": "217258000", "otherCurrentAssets": "10910000", "otherNonCurrentAssets": "None", "totalLiabilities": "126531000", "totalCurrentLiabilities": "35523000", "currentAccountsPayable": "5394000", "deferredRevenue": "None", "currentDebt": "None", "shortTermDebt": "7509000", "totalNonCurrentLiabilities": "91008000", "capitalLeaseObligations": "90756000", "longTermDebt": "None", "currentLongTermDebt": "None", "longTermDebtNoncurrent": "None", "shortLongTermDebtTotal": "90756000", "otherCurrentLiabilities": "22620000", "otherNonCurrentLiabilities": "7761000", "totalShareholderEquity": "422179000", "treasuryStock": "None", "retainedEarnings": "-1819823000", "commonStock": "212000", "commonStockSharesOutstanding": "210572000"}, {"fiscalDateEnding": "2024-09-30", "reportedCurrency": "USD", "totalAssets": "589120000", "totalCurrentAssets": "304415000", "cashAndCashEquivalentsAtCarryingValue": "51239000", "cashAndShortTermInvestments": "51239000", "inventory": "None", "currentNetReceivables": "2800000", "totalNonCurrentAssets": "284705000", "propertyPlantEquipment": "None", "accumulatedDepreciationAmortizationPPE": "None", "intangibleAssets": "None", "intangibleAssetsExcludingGoodwill": "None", "goodwill": "None", "investments": "None", "longTermInvestments": "111821000", "shortTermInvestments": "240325000", "otherCurrentAssets": "12851000", "otherNonCurrentAssets": "None", "totalLiabilities": "125372000", "totalCurrentLiabilities": "32571000", "currentAccountsPayable": "5506000", "deferredRevenue": "None", "currentDebt": "None", "shortTermDebt": "7389000", "totalNonCurrentLiabilities": "92801000", "capitalLeaseObligations": "85135000", "longTermDebt": "None", "currentLongTermDebt": "None", "longTermDebtNoncurrent": "None", "shortLongTermDebtTotal": "85135000", "otherCurrentLiabilities": "27065000", "otherNonCurrentLiabilities": "7666000", "totalShareholderEquity": "463748000", "treasuryStock": "None", "retainedEarnings": "-1759884000", "commonStock": "210000", "commonStockSharesOutstanding": "209189000"}, {"fiscalDateEnding": "2024-06-30", "reportedCurrency": "USD", "totalAssets": "646883000", "totalCurrentAssets": "457124000", "cashAndCashEquivalentsAtCarryingValue": "170667000", "cashAndShortTermInvestments": "170667000", "inventory": "None", "currentNetReceivables": "2000000", "totalNonCurrentAssets": "189759000", "propertyPlantEquipment": "None", "accumulatedDepreciationAmortizationPPE": "None", "intangibleAssets": "None", "intangibleAssetsExcludingGoodwill": "None", "goodwill": "None", "investments": "None", "longTermInvestments": "1134000", "shortTermInvestments": "273961000", "otherCurrentAssets": "10496000", "otherNonCurrentAssets": "None", "totalLiabilities": "131845000", "totalCurrentLiabilities": "37305000", "currentAccountsPayable": "12936000", "deferredRevenue": "None", "currentDebt": "None", "shortTermDebt": "7221000", "totalNonCurrentLiabilities": "94540000", "capitalLeaseObligations": "86989000", "longTermDebt": "None", "currentLongTermDebt": "None", "longTermDebtNoncurrent": "None", "shortLongTermDebtTotal": "94210000", "otherCurrentLiabilities": "17148000", "otherNonCurrentLiabilities": "7551000", "totalShareholderEquity": "515038000", "treasuryStock": "None", "retainedEarnings": "-1693591000", "commonStock": "209000", "commonStockSharesOutstanding": "190027000"}, {"fiscalDateEnding": "2024-03-31", "reportedCurrency": "USD", "totalAssets": "586350000", "totalCurrentAssets": "395364000", "cashAndCashEquivalentsAtCarryingValue": "51039000", "cashAndShortTermInvestments": "51039000", "inventory": "None", "currentNetReceivables": "1700000", "totalNonCurrentAssets": "190986000", "propertyPlantEquipment": "None", "accumulatedDepreciationAmortizationPPE": "None", "intangibleAssets": "None", "intangibleAssetsExcludingGoodwill": "None", "goodwill": "None", "investments": "None", "longTermInvestments": "15121000", "shortTermInvestments": "333821000", "otherCurrentAssets": "8804000", "otherNonCurrentAssets": "None", "totalLiabilities": "124983000", "totalCurrentLiabilities": "30894000", "currentAccountsPayable": "5779000", "deferredRevenue": "None", "currentDebt": "None", "shortTermDebt": "6930000", "totalNonCurrentLiabilities": "94089000", "capitalLeaseObligations": "88916000", "longTermDebt": "None", "currentLongTermDebt": "None", "longTermDebtNoncurrent": "None", "shortLongTermDebtTotal": "95846000", "otherCurrentLiabilities": "18099000", "otherNonCurrentLiabilities": "5173000", "totalShareholderEquity": "461367000", "treasuryStock": "None", "retainedEarnings": "-1627233000", "commonStock": "170000", "commonStockSharesOutstanding": "169128000"}, {"fiscalDateEnding": "2023-12-31", "reportedCurrency": "USD", "totalAssets": "642837000", "totalCurrentAssets": "459115000", "cashAndCashEquivalentsAtCarryingValue": "83155000", "cashAndShortTermInvestments": "83155000", "inventory": "-1700000", "currentNetReceivables": "1700000", "totalNonCurrentAssets": "183722000", "propertyPlantEquipment": "None", "accumulatedDepreciationAmortizationPPE": "None", "intangibleAssets": "None", "intangibleAssetsExcludingGoodwill": "None", "goodwill": "None", "investments": "None", "longTermInvestments": "3645000", "shortTermInvestments": "365542000", "otherCurrentAssets": "10418000", "otherNonCurrentAssets": "None", "totalLiabilities": "130604000", "totalCurrentLiabilities": "37079000", "currentAccountsPayable": "5897000", "deferredRevenue": "None", "currentDebt": "None", "shortTermDebt": "6775000", "totalNonCurrentLiabilities": "93525000", "capitalLeaseObligations": "95121000", "longTermDebt": "None", "currentLongTermDebt": "None", "longTermDebtNoncurrent": "None", "shortLongTermDebtTotal": "95121000", "otherCurrentLiabilities": "24321000", "otherNonCurrentLiabilities": "5179000", "totalShareholderEquity": "512233000", "treasuryStock": "None", "retainedEarnings": "-1562233000", "commonStock": "169000", "commonStockSharesOutstanding": "168336000"}, {"fiscalDateEnding": "2023-09-30", "reportedCurrency": "USD", "totalAssets": "712326000", "totalCurrentAssets": "473454000", "cashAndCashEquivalentsAtCarryingValue": "69246000", "cashAndShortTermInvestments": "69246000", "inventory": "-1600000", "currentNetReceivables": "1600000", "totalNonCurrentAssets": "238872000", "propertyPlantEquipment": "None", "accumulatedDepreciationAmortizationPPE": "None", "intangibleAssets": "None", "intangibleAssetsExcludingGoodwill": "None", "goodwill": "None", "investments": "None", "longTermInvestments": "37535000", "shortTermInvestments": "396259000", "otherCurrentAssets": "7949000", "otherNonCurrentAssets": "None", "totalLiabilities": "129224000", "totalCurrentLiabilities": "37636000", "currentAccountsPayable": "6205000", "deferredRevenue": "None", "currentDebt": "None", "shortTermDebt": "6578000", "totalNonCurrentLiabilities": "91588000", "capitalLeaseObligations": "90102000", "longTermDebt": "None", "currentLongTermDebt": "None", "longTermDebtNoncurrent": "None", "shortLongTermDebtTotal": "96680000", "otherCurrentLiabilities": "24617000", "otherNonCurrentLiabilities": "1486000", "totalShareholderEquity": "583102000", "treasuryStock": "None", "retainedEarnings": "-1473988000", "commonStock": "168000", "commonStockSharesOutstanding": "167649000"}, {"fiscalDateEnding": "2023-06-30", "reportedCurrency": "USD", "totalAssets": "770971000", "totalCurrentAssets": "502101000", "cashAndCashEquivalentsAtCarryingValue": "154758000", "cashAndShortTermInvestments": "154758000", "inventory": "-1100000", "currentNetReceivables": "1100000", "totalNonCurrentAssets": "268870000", "propertyPlantEquipment": "106386000", "accumulatedDepreciationAmortizationPPE": "None", "intangibleAssets": "None", "intangibleAssetsExcludingGoodwill": "None", "goodwill": "None", "investments": "None", "longTermInvestments": "62496000", "shortTermInvestments": "337204000", "otherCurrentAssets": "10139000", "otherNonCurrentAssets": "None", "totalLiabilities": "148065000", "totalCurrentLiabilities": "54721000", "currentAccountsPayable": "10229000", "deferredRevenue": "None", "currentDebt": "None", "shortTermDebt": "6381000", "totalNonCurrentLiabilities": "93344000", "capitalLeaseObligations": "91821000", "longTermDebt": "None", "currentLongTermDebt": "None", "longTermDebtNoncurrent": "None", "shortLongTermDebtTotal": "91821000", "otherCurrentLiabilities": "44263000", "otherNonCurrentLiabilities": "93344000", "totalShareholderEquity": "622906000", "treasuryStock": "None", "retainedEarnings": "-1412673000", "commonStock": "167000", "commonStockSharesOutstanding": "146796000"}, {"fiscalDateEnding": "2023-03-31", "reportedCurrency": "USD", "totalAssets": "746871000", "totalCurrentAssets": "481465000", "cashAndCashEquivalentsAtCarryingValue": "109931000", "cashAndShortTermInvestments": "109931000", "inventory": "-12441000", "currentNetReceivables": "2200000", "totalNonCurrentAssets": "265406000", "propertyPlantEquipment": "109849000", "accumulatedDepreciationAmortizationPPE": "None", "intangibleAssets": "None", "intangibleAssetsExcludingGoodwill": "None", "goodwill": "None", "investments": "None", "longTermInvestments": "53912000", "shortTermInvestments": "361293000", "otherCurrentAssets": "10241000", "otherNonCurrentAssets": "None", "totalLiabilities": "154609000", "totalCurrentLiabilities": "59585000", "currentAccountsPayable": "14688000", "deferredRevenue": "None", "currentDebt": "None", "shortTermDebt": "6189000", "totalNonCurrentLiabilities": "95024000", "capitalLeaseObligations": "99703000", "longTermDebt": "None", "currentLongTermDebt": "None", "longTermDebtNoncurrent": "None", "shortLongTermDebtTotal": "99703000", "otherCurrentLiabilities": "38435000", "otherNonCurrentLiabilities": "95024000", "totalShareholderEquity": "592262000", "treasuryStock": "None", "retainedEarnings": "-1334684000", "commonStock": "146000", "commonStockSharesOutstanding": "144564000"}, {"fiscalDateEnding": "2022-12-31", "reportedCurrency": "USD", "totalAssets": "821579000", "totalCurrentAssets": "528824000", "cashAndCashEquivalentsAtCarryingValue": "61904000", "cashAndShortTermInvestments": "61904000", "inventory": "-62451000", "currentNetReceivables": "3300000", "totalNonCurrentAssets": "292755000", "propertyPlantEquipment": "196431000", "accumulatedDepreciationAmortizationPPE": "None", "intangibleAssets": "None", "intangibleAssetsExcludingGoodwill": "None", "goodwill": "None", "investments": "None", "longTermInvestments": "71968000", "shortTermInvestments": "455416000", "otherCurrentAssets": "11504000", "otherNonCurrentAssets": "None", "totalLiabilities": "154697000", "totalCurrentLiabilities": "53728000", "currentAccountsPayable": "13890000", "deferredRevenue": "None", "currentDebt": "None", "shortTermDebt": "6002000", "totalNonCurrentLiabilities": "100969000", "capitalLeaseObligations": "101124000", "longTermDebt": "None", "currentLongTermDebt": "None", "longTermDebtNoncurrent": "None", "shortLongTermDebtTotal": "101124000", "otherCurrentLiabilities": "33741000", "otherNonCurrentLiabilities": "1569000", "totalShareholderEquity": "666882000", "treasuryStock": "None", "retainedEarnings": "-1234968000", "commonStock": "144000", "commonStockSharesOutstanding": "144149000"}, {"fiscalDateEnding": "2022-09-30", "reportedCurrency": "USD", "totalAssets": "887572000", "totalCurrentAssets": "569061000", "cashAndCashEquivalentsAtCarryingValue": "74357000", "cashAndShortTermInvestments": "74357000", "inventory": "-5800000", "currentNetReceivables": "5800000", "totalNonCurrentAssets": "318511000", "propertyPlantEquipment": "114442000", "accumulatedDepreciationAmortizationPPE": "None", "intangibleAssets": "None", "intangibleAssetsExcludingGoodwill": "None", "goodwill": "None", "investments": "None", "longTermInvestments": "99154000", "shortTermInvestments": "477872000", "otherCurrentAssets": "16832000", "otherNonCurrentAssets": "None", "totalLiabilities": "147611000", "totalCurrentLiabilities": "48872000", "currentAccountsPayable": "11045000", "deferredRevenue": "None", "currentDebt": "None", "shortTermDebt": "5831000", "totalNonCurrentLiabilities": "98739000", "capitalLeaseObligations": "96706000", "longTermDebt": "None", "currentLongTermDebt": "None", "longTermDebtNoncurrent": "None", "shortLongTermDebtTotal": "96706000", "otherCurrentLiabilities": "36938000", "otherNonCurrentLiabilities": "98739000", "totalShareholderEquity": "739961000", "treasuryStock": "None", "retainedEarnings": "-1141133000", "commonStock": "144000", "commonStockSharesOutstanding": "143662000"}, {"fiscalDateEnding": "2022-06-30", "reportedCurrency": "USD", "totalAssets": "947644000", "totalCurrentAssets": "513028000", "cashAndCashEquivalentsAtCarryingValue": "96041000", "cashAndShortTermInvestments": "96041000", "inventory": "-11900000", "currentNetReceivables": "11900000", "totalNonCurrentAssets": "434616000", "propertyPlantEquipment": "117216000", "accumulatedDepreciationAmortizationPPE": "None", "intangibleAssets": "None", "intangibleAssetsExcludingGoodwill": "None", "goodwill": "None", "investments": "None", "longTermInvestments": "211333000", "shortTermInvestments": "394451000", "otherCurrentAssets": "22536000", "otherNonCurrentAssets": "None", "totalLiabilities": "145695000", "totalCurrentLiabilities": "44909000", "currentAccountsPayable": "9713000", "deferredRevenue": "None", "currentDebt": "None", "shortTermDebt": "5344000", "totalNonCurrentLiabilities": "100786000", "capitalLeaseObligations": "98232000", "longTermDebt": "None", "currentLongTermDebt": "None", "longTermDebtNoncurrent": "None", "shortLongTermDebtTotal": "98232000", "otherCurrentLiabilities": "34360000", "otherNonCurrentLiabilities": "100786000", "totalShareholderEquity": "801949000", "treasuryStock": "None", "retainedEarnings": "-1057985000", "commonStock": "144000", "commonStockSharesOutstanding": "143385000"}, {"fiscalDateEnding": "2022-03-31", "reportedCurrency": "USD", "totalAssets": "964632000", "totalCurrentAssets": "469744000", "cashAndCashEquivalentsAtCarryingValue": "84514000", "cashAndShortTermInvestments": "84514000", "inventory": "-11300000", "currentNetReceivables": "9042000", "totalNonCurrentAssets": "494888000", "propertyPlantEquipment": "120200000", "accumulatedDepreciationAmortizationPPE": "None", "intangibleAssets": "None", "intangibleAssetsExcludingGoodwill": "None", "goodwill": "None", "investments": "None", "longTermInvestments": "298297000", "shortTermInvestments": "364536000", "otherCurrentAssets": "20694000", "otherNonCurrentAssets": "None", "totalLiabilities": "109402000", "totalCurrentLiabilities": "36877000", "currentAccountsPayable": "8708000", "deferredRevenue": "None", "currentDebt": "None", "shortTermDebt": "None", "totalNonCurrentLiabilities": "72525000", "capitalLeaseObligations": "69035000", "longTermDebt": "None", "currentLongTermDebt": "None", "longTermDebtNoncurrent": "None", "shortLongTermDebtTotal": "69035000", "otherCurrentLiabilities": "27763000", "otherNonCurrentLiabilities": "72525000", "totalShareholderEquity": "855230000", "treasuryStock": "None", "retainedEarnings": "-983198000", "commonStock": "143000", "commonStockSharesOutstanding": "141356000"}, {"fiscalDateEnding": "2021-12-31", "reportedCurrency": "USD", "totalAssets": "1050828000", "totalCurrentAssets": "471323000", "cashAndCashEquivalentsAtCarryingValue": "173314000", "cashAndShortTermInvestments": "173314000", "inventory": "-20021000", "currentNetReceivables": "5815000", "totalNonCurrentAssets": "579505000", "propertyPlantEquipment": "122990000", "accumulatedDepreciationAmortizationPPE": "None", "intangibleAssets": "None", "intangibleAssetsExcludingGoodwill": "None", "goodwill": "None", "investments": "None", "longTermInvestments": "352179000", "shortTermInvestments": "283988000", "otherCurrentAssets": "14021000", "otherNonCurrentAssets": "None", "totalLiabilities": "125628000", "totalCurrentLiabilities": "47907000", "currentAccountsPayable": "10255000", "deferredRevenue": "None", "currentDebt": "None", "shortTermDebt": "3200000", "totalNonCurrentLiabilities": "77721000", "capitalLeaseObligations": "69929000", "longTermDebt": "None", "currentLongTermDebt": "None", "longTermDebtNoncurrent": "None", "shortLongTermDebtTotal": "73129000", "otherCurrentLiabilities": "34296000", "otherNonCurrentLiabilities": "74054000", "totalShareholderEquity": "925200000", "treasuryStock": "None", "retainedEarnings": "-894554000", "commonStock": "142000", "commonStockSharesOutstanding": "139174000"}, {"fiscalDateEnding": "2021-09-30", "reportedCurrency": "USD", "totalAssets": "1079246000", "totalCurrentAssets": "502858000", "cashAndCashEquivalentsAtCarryingValue": "190021000", "cashAndShortTermInvestments": "190021000", "inventory": "-9400000", "currentNetReceivables": "6160000", "totalNonCurrentAssets": "576388000", "propertyPlantEquipment": "125883000", "accumulatedDepreciationAmortizationPPE": "None", "intangibleAssets": "None", "intangibleAssetsExcludingGoodwill": "None", "goodwill": "None", "investments": "None", "longTermInvestments": "396132000", "shortTermInvestments": "293464000", "otherCurrentAssets": "19373000", "otherNonCurrentAssets": "None", "totalLiabilities": "109304000", "totalCurrentLiabilities": "53490000", "currentAccountsPayable": "11499000", "deferredRevenue": "None", "currentDebt": "None", "shortTermDebt": "None", "totalNonCurrentLiabilities": "55814000", "capitalLeaseObligations": "50639000", "longTermDebt": "None", "currentLongTermDebt": "None", "longTermDebtNoncurrent": "None", "shortLongTermDebtTotal": "50639000", "otherCurrentLiabilities": "41626000", "otherNonCurrentLiabilities": "55814000", "totalShareholderEquity": "969942000", "treasuryStock": "None", "retainedEarnings": "-828480000", "commonStock": "142000", "commonStockSharesOutstanding": "137026000"}, {"fiscalDateEnding": "2021-06-30", "reportedCurrency": "USD", "totalAssets": "1126724000", "totalCurrentAssets": "602171000", "cashAndCashEquivalentsAtCarryingValue": "223503000", "cashAndShortTermInvestments": "223503000", "inventory": "-4300000", "currentNetReceivables": "4300000", "totalNonCurrentAssets": "524553000", "propertyPlantEquipment": "164933000", "accumulatedDepreciationAmortizationPPE": "None", "intangibleAssets": "None", "intangibleAssetsExcludingGoodwill": "None", "goodwill": "None", "investments": "None", "longTermInvestments": "344342000", "shortTermInvestments": "364204000", "otherCurrentAssets": "14464000", "otherNonCurrentAssets": "None", "totalLiabilities": "102912000", "totalCurrentLiabilities": "45998000", "currentAccountsPayable": "11005000", "deferredRevenue": "None", "currentDebt": "None", "shortTermDebt": "None", "totalNonCurrentLiabilities": "56914000", "capitalLeaseObligations": "51209000", "longTermDebt": "None", "currentLongTermDebt": "None", "longTermDebtNoncurrent": "None", "shortLongTermDebtTotal": "51209000", "otherCurrentLiabilities": "34688000", "otherNonCurrentLiabilities": "5705000", "totalShareholderEquity": "1023812000", "treasuryStock": "None", "retainedEarnings": "-750294000", "commonStock": "142000", "commonStockSharesOutstanding": "134827000"}, {"fiscalDateEnding": "2021-03-31", "reportedCurrency": "USD", "totalAssets": "1179044000", "totalCurrentAssets": "716061000", "cashAndCashEquivalentsAtCarryingValue": "236865000", "cashAndShortTermInvestments": "236865000", "inventory": "-4500000", "currentNetReceivables": "6275000", "totalNonCurrentAssets": "462983000", "propertyPlantEquipment": "123146000", "accumulatedDepreciationAmortizationPPE": "None", "intangibleAssets": "None", "intangibleAssetsExcludingGoodwill": "None", "goodwill": "None", "investments": "None", "longTermInvestments": "283924000", "shortTermInvestments": "462716000", "otherCurrentAssets": "16480000", "otherNonCurrentAssets": "None", "totalLiabilities": "109265000", "totalCurrentLiabilities": "54849000", "currentAccountsPayable": "14875000", "deferredRevenue": "None", "currentDebt": "None", "shortTermDebt": "51625000", "totalNonCurrentLiabilities": "54416000", "capitalLeaseObligations": "51625000", "longTermDebt": "None", "currentLongTermDebt": "None", "longTermDebtNoncurrent": "None", "shortLongTermDebtTotal": "51625000", "otherCurrentLiabilities": "39735000", "otherNonCurrentLiabilities": "54416000", "totalShareholderEquity": "1069779000", "treasuryStock": "None", "retainedEarnings": "-679358000", "commonStock": "141000", "commonStockSharesOutstanding": "132165000"}, {"fiscalDateEnding": "2020-12-31", "reportedCurrency": "USD", "totalAssets": "1227829000", "totalCurrentAssets": "845130000", "cashAndCashEquivalentsAtCarryingValue": "183351000", "cashAndShortTermInvestments": "183351000", "inventory": "None", "currentNetReceivables": "5169000", "totalNonCurrentAssets": "382699000", "propertyPlantEquipment": "118840000", "accumulatedDepreciationAmortizationPPE": "None", "intangibleAssets": "None", "intangibleAssetsExcludingGoodwill": "None", "goodwill": "None", "investments": "None", "longTermInvestments": "204208000", "shortTermInvestments": "644559000", "otherCurrentAssets": "17220000", "otherNonCurrentAssets": "None", "totalLiabilities": "148212000", "totalCurrentLiabilities": "94320000", "currentAccountsPayable": "10390000", "deferredRevenue": "None", "currentDebt": "None", "shortTermDebt": "2974000", "totalNonCurrentLiabilities": "53892000", "capitalLeaseObligations": "53783000", "longTermDebt": "None", "currentLongTermDebt": "None", "longTermDebtNoncurrent": "None", "shortLongTermDebtTotal": "53783000", "otherCurrentLiabilities": "41964000", "otherNonCurrentLiabilities": "53892000", "totalShareholderEquity": "1079617000", "treasuryStock": "None", "retainedEarnings": "-646343000", "commonStock": "140000", "commonStockSharesOutstanding": "129835000"}, {"fiscalDateEnding": "2020-09-30", "reportedCurrency": "USD", "totalAssets": "1222500000", "totalCurrentAssets": "854058000", "cashAndCashEquivalentsAtCarryingValue": "158136000", "cashAndShortTermInvestments": "158136000", "inventory": "None", "currentNetReceivables": "2274000", "totalNonCurrentAssets": "368442000", "propertyPlantEquipment": "102653000", "accumulatedDepreciationAmortizationPPE": "None", "intangibleAssets": "None", "intangibleAssetsExcludingGoodwill": "None", "goodwill": "None", "investments": "None", "longTermInvestments": "212509000", "shortTermInvestments": "682886000", "otherCurrentAssets": "13036000", "otherNonCurrentAssets": "None", "totalLiabilities": "103769000", "totalCurrentLiabilities": "50130000", "currentAccountsPayable": "10151000", "deferredRevenue": "None", "currentDebt": "None", "shortTermDebt": "50846000", "totalNonCurrentLiabilities": "53639000", "capitalLeaseObligations": "50846000", "longTermDebt": "None", "currentLongTermDebt": "None", "longTermDebtNoncurrent": "None", "shortLongTermDebtTotal": "50846000", "otherCurrentLiabilities": "39979000", "otherNonCurrentLiabilities": "53639000", "totalShareholderEquity": "1118731000", "treasuryStock": "None", "retainedEarnings": "-577773000", "commonStock": "140000", "commonStockSharesOutstanding": "127141000"}, {"fiscalDateEnding": "2020-06-30", "reportedCurrency": "USD", "totalAssets": "1258544000", "totalCurrentAssets": "909577000", "cashAndCashEquivalentsAtCarryingValue": "280379000", "cashAndShortTermInvestments": "280379000", "inventory": "None", "currentNetReceivables": "800000", "totalNonCurrentAssets": "348967000", "propertyPlantEquipment": "127037000", "accumulatedDepreciationAmortizationPPE": "None", "intangibleAssets": "None", "intangibleAssetsExcludingGoodwill": "None", "goodwill": "None", "investments": "None", "longTermInvestments": "215471000", "shortTermInvestments": "619271000", "otherCurrentAssets": "9927000", "otherNonCurrentAssets": "None", "totalLiabilities": "95125000", "totalCurrentLiabilities": "40895000", "currentAccountsPayable": "9057000", "deferredRevenue": "None", "currentDebt": "None", "shortTermDebt": "None", "totalNonCurrentLiabilities": "54230000", "capitalLeaseObligations": "51067000", "longTermDebt": "None", "currentLongTermDebt": "None", "longTermDebtNoncurrent": "None", "shortLongTermDebtTotal": "51067000", "otherCurrentLiabilities": "31838000", "otherNonCurrentLiabilities": "3163000", "totalShareholderEquity": "1163419000", "treasuryStock": "None", "retainedEarnings": "-511576000", "commonStock": "139000", "commonStockSharesOutstanding": "115377000"}, {"fiscalDateEnding": "2020-03-31", "reportedCurrency": "USD", "totalAssets": "688523000", "totalCurrentAssets": "504414000", "cashAndCashEquivalentsAtCarryingValue": "135897000", "cashAndShortTermInvestments": "135897000", "inventory": "None", "currentNetReceivables": "200000", "totalNonCurrentAssets": "184109000", "propertyPlantEquipment": "110185000", "accumulatedDepreciationAmortizationPPE": "None", "intangibleAssets": "None", "intangibleAssetsExcludingGoodwill": "None", "goodwill": "None", "investments": "None", "longTermInvestments": "64950000", "shortTermInvestments": "357026000", "otherCurrentAssets": "11491000", "otherNonCurrentAssets": "None", "totalLiabilities": "82004000", "totalCurrentLiabilities": "26818000", "currentAccountsPayable": "7199000", "deferredRevenue": "None", "currentDebt": "None", "shortTermDebt": "None", "totalNonCurrentLiabilities": "55186000", "capitalLeaseObligations": "51536000", "longTermDebt": "None", "currentLongTermDebt": "None", "longTermDebtNoncurrent": "None", "shortLongTermDebtTotal": "51536000", "otherCurrentLiabilities": "19619000", "otherNonCurrentLiabilities": "3650000", "totalShareholderEquity": "606519000", "treasuryStock": "None", "retainedEarnings": "-450602000", "commonStock": "125000", "commonStockSharesOutstanding": "108964000"}, {"fiscalDateEnding": "2019-12-31", "reportedCurrency": "USD", "totalAssets": "717802000", "totalCurrentAssets": "544576000", "cashAndCashEquivalentsAtCarryingValue": "175126000", "cashAndShortTermInvestments": "175126000", "inventory": "-58322000", "currentNetReceivables": "2403000", "totalNonCurrentAssets": "173226000", "propertyPlantEquipment": "100944000", "accumulatedDepreciationAmortizationPPE": "None", "intangibleAssets": "151000", "intangibleAssetsExcludingGoodwill": "151000", "goodwill": "None", "investments": "None", "longTermInvestments": "63214000", "shortTermInvestments": "355407000", "otherCurrentAssets": "11640000", "otherNonCurrentAssets": "None", "totalLiabilities": "88779000", "totalCurrentLiabilities": "33079000", "currentAccountsPayable": "9250000", "deferredRevenue": "None", "currentDebt": "None", "shortTermDebt": "1679000", "totalNonCurrentLiabilities": "55700000", "capitalLeaseObligations": "51349000", "longTermDebt": "None", "currentLongTermDebt": "None", "longTermDebtNoncurrent": "None", "shortLongTermDebtTotal": "53028000", "otherCurrentLiabilities": "22150000", "otherNonCurrentLiabilities": "4351000", "totalShareholderEquity": "629023000", "treasuryStock": "None", "retainedEarnings": "-396122000", "commonStock": "124000", "commonStockSharesOutstanding": "104801000"}, {"fiscalDateEnding": "2019-09-30", "reportedCurrency": "USD", "totalAssets": "695544000", "totalCurrentAssets": "509757000", "cashAndCashEquivalentsAtCarryingValue": "160990000", "cashAndShortTermInvestments": "160990000", "inventory": "None", "currentNetReceivables": "2337000", "totalNonCurrentAssets": "185787000", "propertyPlantEquipment": "77380000", "accumulatedDepreciationAmortizationPPE": "None", "intangibleAssets": "301000", "intangibleAssetsExcludingGoodwill": "301000", "goodwill": "None", "investments": "None", "longTermInvestments": "100702000", "shortTermInvestments": "340254000", "otherCurrentAssets": "6176000", "otherNonCurrentAssets": "None", "totalLiabilities": "75828000", "totalCurrentLiabilities": "33354000", "currentAccountsPayable": "8047000", "deferredRevenue": "None", "currentDebt": "None", "shortTermDebt": "None", "totalNonCurrentLiabilities": "42474000", "capitalLeaseObligations": "37689000", "longTermDebt": "None", "currentLongTermDebt": "None", "longTermDebtNoncurrent": "None", "shortLongTermDebtTotal": "37689000", "otherCurrentLiabilities": "25307000", "otherNonCurrentLiabilities": "4785000", "totalShareholderEquity": "619716000", "treasuryStock": "None", "retainedEarnings": "-335092000", "commonStock": "122000", "commonStockSharesOutstanding": "102187000"}, {"fiscalDateEnding": "2019-06-30", "reportedCurrency": "USD", "totalAssets": "733997000", "totalCurrentAssets": "511542000", "cashAndCashEquivalentsAtCarryingValue": "650193000", "cashAndShortTermInvestments": "650193000", "inventory": "-147769000", "currentNetReceivables": "3285000", "totalNonCurrentAssets": "222455000", "propertyPlantEquipment": "67697000", "accumulatedDepreciationAmortizationPPE": "None", "intangibleAssets": "452000", "intangibleAssetsExcludingGoodwill": "452000", "goodwill": "None", "investments": "None", "longTermInvestments": "147769000", "shortTermInvestments": "389840000", "otherCurrentAssets": "5833000", "otherNonCurrentAssets": "None", "totalLiabilities": "78362000", "totalCurrentLiabilities": "38000000", "currentAccountsPayable": "23503000", "deferredRevenue": "None", "currentDebt": "None", "shortTermDebt": "None", "totalNonCurrentLiabilities": "40362000", "capitalLeaseObligations": "34867000", "longTermDebt": "None", "currentLongTermDebt": "None", "longTermDebtNoncurrent": "None", "shortLongTermDebtTotal": "34867000", "otherCurrentLiabilities": "14497000", "otherNonCurrentLiabilities": "5495000", "totalShareholderEquity": "655635000", "treasuryStock": "None", "retainedEarnings": "-284357000", "commonStock": "122000", "commonStockSharesOutstanding": "99847000"}, {"fiscalDateEnding": "2019-03-31", "reportedCurrency": "USD", "totalAssets": "749369000", "totalCurrentAssets": "476627000", "cashAndCashEquivalentsAtCarryingValue": "92748000", "cashAndShortTermInvestments": "92748000", "inventory": "None", "currentNetReceivables": "3391000", "totalNonCurrentAssets": "272742000", "propertyPlantEquipment": "52820000", "accumulatedDepreciationAmortizationPPE": "None", "intangibleAssets": "603000", "intangibleAssetsExcludingGoodwill": "603000", "goodwill": "None", "investments": "None", "longTermInvestments": "214588000", "shortTermInvestments": "373392000", "otherCurrentAssets": "7096000", "otherNonCurrentAssets": "None", "totalLiabilities": "68141000", "totalCurrentLiabilities": "27265000", "currentAccountsPayable": "12976000", "deferredRevenue": "None", "currentDebt": "None", "shortTermDebt": "None", "totalNonCurrentLiabilities": "40876000", "capitalLeaseObligations": "34811000", "longTermDebt": "34811000", "currentLongTermDebt": "None", "longTermDebtNoncurrent": "None", "shortLongTermDebtTotal": "34811000", "otherCurrentLiabilities": "14289000", "otherNonCurrentLiabilities": "6065000", "totalShareholderEquity": "681228000", "treasuryStock": "None", "retainedEarnings": "-243114000", "commonStock": "121000", "commonStockSharesOutstanding": "97316000"}, {"fiscalDateEnding": "2018-12-31", "reportedCurrency": "USD", "totalAssets": "773855000", "totalCurrentAssets": "467982000", "cashAndCashEquivalentsAtCarryingValue": "721350000", "cashAndShortTermInvestments": "721350000", "inventory": "-261966000", "currentNetReceivables": "3108000", "totalNonCurrentAssets": "305873000", "propertyPlantEquipment": "8595000", "accumulatedDepreciationAmortizationPPE": "None", "intangibleAssets": "754000", "intangibleAssetsExcludingGoodwill": "754000", "goodwill": "None", "investments": "None", "longTermInvestments": "261966000", "shortTermInvestments": "366952000", "otherCurrentAssets": "5490000", "otherNonCurrentAssets": "None", "totalLiabilities": "70691000", "totalCurrentLiabilities": "29459000", "currentAccountsPayable": "12338000", "deferredRevenue": "None", "currentDebt": "None", "shortTermDebt": "None", "totalNonCurrentLiabilities": "41232000", "capitalLeaseObligations": "None", "longTermDebt": "34456000", "currentLongTermDebt": "None", "longTermDebtNoncurrent": "None", "shortLongTermDebtTotal": "34456000", "otherCurrentLiabilities": "17121000", "otherNonCurrentLiabilities": "41232000", "totalShareholderEquity": "703164000", "treasuryStock": "None", "retainedEarnings": "-211528000", "commonStock": "121000", "commonStockSharesOutstanding": "82064000"}, {"fiscalDateEnding": "2018-09-30", "reportedCurrency": "USD", "totalAssets": "435235000", "totalCurrentAssets": "247353000", "cashAndCashEquivalentsAtCarryingValue": "83141000", "cashAndShortTermInvestments": "83141000", "inventory": "None", "currentNetReceivables": "None", "totalNonCurrentAssets": "187882000", "propertyPlantEquipment": "4693000", "accumulatedDepreciationAmortizationPPE": "None", "intangibleAssets": "904000", "intangibleAssetsExcludingGoodwill": "904000", "goodwill": "None", "investments": "None", "longTermInvestments": "154045000", "shortTermInvestments": "161080000", "otherCurrentAssets": "6264000", "otherNonCurrentAssets": "None", "totalLiabilities": "603678000", "totalCurrentLiabilities": "159477000", "currentAccountsPayable": "3083000", "deferredRevenue": "None", "currentDebt": "None", "shortTermDebt": "139615000", "totalNonCurrentLiabilities": "444201000", "capitalLeaseObligations": "None", "longTermDebt": "25661000", "currentLongTermDebt": "None", "longTermDebtNoncurrent": "None", "shortLongTermDebtTotal": "165276000", "otherCurrentLiabilities": "16779000", "otherNonCurrentLiabilities": "33149000", "totalShareholderEquity": "-168443000", "treasuryStock": "None", "retainedEarnings": "-181019000", "commonStock": "31000", "commonStockSharesOutstanding": "113689000"}, {"fiscalDateEnding": "2018-06-30", "reportedCurrency": "USD", "totalAssets": "298845000", "totalCurrentAssets": "294264000", "cashAndCashEquivalentsAtCarryingValue": "293927000", "cashAndShortTermInvestments": "293927000", "inventory": "None", "currentNetReceivables": "None", "totalNonCurrentAssets": "4581000", "propertyPlantEquipment": "3526000", "accumulatedDepreciationAmortizationPPE": "None", "intangibleAssets": "1055000", "intangibleAssetsExcludingGoodwill": "1055000", "goodwill": "None", "investments": "None", "longTermInvestments": "None", "shortTermInvestments": "None", "otherCurrentAssets": "337000", "otherNonCurrentAssets": "None", "totalLiabilities": "17233000", "totalCurrentLiabilities": "14745000", "currentAccountsPayable": "1268000", "deferredRevenue": "None", "currentDebt": "None", "shortTermDebt": "None", "totalNonCurrentLiabilities": "2488000", "capitalLeaseObligations": "None", "longTermDebt": "None", "currentLongTermDebt": "None", "longTermDebtNoncurrent": "None", "shortLongTermDebtTotal": "None", "otherCurrentLiabilities": "13477000", "otherNonCurrentLiabilities": "None", "totalShareholderEquity": "281612000", "treasuryStock": "None", "retainedEarnings": "-137522000", "commonStock": "89000", "commonStockSharesOutstanding": "113689000"}, {"fiscalDateEnding": "2018-03-31", "reportedCurrency": "USD", "totalAssets": "148845000", "totalCurrentAssets": "144264000", "cashAndCashEquivalentsAtCarryingValue": "143927000", "cashAndShortTermInvestments": "143927000", "inventory": "None", "currentNetReceivables": "None", "totalNonCurrentAssets": "None", "propertyPlantEquipment": "3526000", "accumulatedDepreciationAmortizationPPE": "None", "intangibleAssets": "1055000", "intangibleAssetsExcludingGoodwill": "1055000", "goodwill": "None", "investments": "None", "longTermInvestments": "None", "shortTermInvestments": "None", "otherCurrentAssets": "None", "otherNonCurrentAssets": "None", "totalLiabilities": "17233000", "totalCurrentLiabilities": "14745000", "currentAccountsPayable": "1268000", "deferredRevenue": "None", "currentDebt": "None", "shortTermDebt": "None", "totalNonCurrentLiabilities": "None", "capitalLeaseObligations": "None", "longTermDebt": "None", "currentLongTermDebt": "None", "longTermDebtNoncurrent": "None", "shortLongTermDebtTotal": "None", "otherCurrentLiabilities": "3079000", "otherNonCurrentLiabilities": "None", "totalShareholderEquity": "-2000", "treasuryStock": "None", "retainedEarnings": "-137501000", "commonStock": "5000", "commonStockSharesOutstanding": "44011000"}, {"fiscalDateEnding": "2017-12-31", "reportedCurrency": "USD", "totalAssets": "None", "totalCurrentAssets": "None", "cashAndCashEquivalentsAtCarryingValue": "None", "cashAndShortTermInvestments": "None", "inventory": "None", "currentNetReceivables": "None", "totalNonCurrentAssets": "None", "propertyPlantEquipment": "None", "accumulatedDepreciationAmortizationPPE": "None", "intangibleAssets": "None", "intangibleAssetsExcludingGoodwill": "None", "goodwill": "None", "investments": "None", "longTermInvestments": "None", "shortTermInvestments": "None", "otherCurrentAssets": "None", "otherNonCurrentAssets": "None", "totalLiabilities": "2000", "totalCurrentLiabilities": "2000", "currentAccountsPayable": "None", "deferredRevenue": "None", "currentDebt": "None", "shortTermDebt": "None", "totalNonCurrentLiabilities": "None", "capitalLeaseObligations": "None", "longTermDebt": "None", "currentLongTermDebt": "None", "longTermDebtNoncurrent": "None", "shortLongTermDebtTotal": "None", "otherCurrentLiabilities": "2000", "otherNonCurrentLiabilities": "None", "totalShareholderEquity": "-2000", "treasuryStock": "None", "retainedEarnings": "-2000", "commonStock": "26000", "commonStockSharesOutstanding": "44011274"}]}