{"symbol": "ANTX", "annualReports": [{"fiscalDateEnding": "2024-12-31", "reportedCurrency": "USD", "totalAssets": "92087000", "totalCurrentAssets": "86262000", "cashAndCashEquivalentsAtCarryingValue": "21351000", "cashAndShortTermInvestments": "21351000", "inventory": "None", "currentNetReceivables": "300000", "totalNonCurrentAssets": "5825000", "propertyPlantEquipment": "None", "accumulatedDepreciationAmortizationPPE": "None", "intangibleAssets": "None", "intangibleAssetsExcludingGoodwill": "None", "goodwill": "None", "investments": "None", "longTermInvestments": "5021000", "shortTermInvestments": "62267000", "otherCurrentAssets": "2344000", "otherNonCurrentAssets": "None", "totalLiabilities": "10238000", "totalCurrentLiabilities": "10238000", "currentAccountsPayable": "3317000", "deferredRevenue": "None", "currentDebt": "None", "shortTermDebt": "None", "totalNonCurrentLiabilities": "0", "capitalLeaseObligations": "None", "longTermDebt": "None", "currentLongTermDebt": "None", "longTermDebtNoncurrent": "None", "shortLongTermDebtTotal": "None", "otherCurrentLiabilities": "6921000", "otherNonCurrentLiabilities": "None", "totalShareholderEquity": "81849000", "treasuryStock": "None", "retainedEarnings": "-205776000", "commonStock": "None", "commonStockSharesOutstanding": "29828000"}, {"fiscalDateEnding": "2023-12-31", "reportedCurrency": "USD", "totalAssets": "138744000", "totalCurrentAssets": "110507000", "cashAndCashEquivalentsAtCarryingValue": "15647000", "cashAndShortTermInvestments": "15647000", "inventory": "None", "currentNetReceivables": "1400000", "totalNonCurrentAssets": "28237000", "propertyPlantEquipment": "None", "accumulatedDepreciationAmortizationPPE": "None", "intangibleAssets": "None", "intangibleAssetsExcludingGoodwill": "None", "goodwill": "None", "investments": "None", "longTermInvestments": "27194000", "shortTermInvestments": "91648000", "otherCurrentAssets": "1812000", "otherNonCurrentAssets": "None", "totalLiabilities": "14043000", "totalCurrentLiabilities": "14043000", "currentAccountsPayable": "2676000", "deferredRevenue": "None", "currentDebt": "None", "shortTermDebt": "None", "totalNonCurrentLiabilities": "0", "capitalLeaseObligations": "0", "longTermDebt": "None", "currentLongTermDebt": "None", "longTermDebtNoncurrent": "None", "shortLongTermDebtTotal": "None", "otherCurrentLiabilities": "11367000", "otherNonCurrentLiabilities": "None", "totalShareholderEquity": "124701000", "treasuryStock": "None", "retainedEarnings": "-154455000", "commonStock": "None", "commonStockSharesOutstanding": "23600000"}, {"fiscalDateEnding": "2022-12-31", "reportedCurrency": "USD", "totalAssets": "102560000", "totalCurrentAssets": "98621000", "cashAndCashEquivalentsAtCarryingValue": "27219000", "cashAndShortTermInvestments": "27219000", "inventory": "None", "currentNetReceivables": "None", "totalNonCurrentAssets": "3939000", "propertyPlantEquipment": "None", "accumulatedDepreciationAmortizationPPE": "None", "intangibleAssets": "None", "intangibleAssetsExcludingGoodwill": "None", "goodwill": "None", "investments": "None", "longTermInvestments": "3219000", "shortTermInvestments": "68840000", "otherCurrentAssets": "2562000", "otherNonCurrentAssets": "None", "totalLiabilities": "7188000", "totalCurrentLiabilities": "7186000", "currentAccountsPayable": "2122000", "deferredRevenue": "None", "currentDebt": "None", "shortTermDebt": "53000", "totalNonCurrentLiabilities": "2000", "capitalLeaseObligations": "53000", "longTermDebt": "None", "currentLongTermDebt": "None", "longTermDebtNoncurrent": "None", "shortLongTermDebtTotal": "53000", "otherCurrentLiabilities": "5011000", "otherNonCurrentLiabilities": "2000", "totalShareholderEquity": "95372000", "treasuryStock": "None", "retainedEarnings": "-89723000", "commonStock": "None", "commonStockSharesOutstanding": "15340000"}, {"fiscalDateEnding": "2021-12-31", "reportedCurrency": "USD", "totalAssets": "65316000", "totalCurrentAssets": "60106000", "cashAndCashEquivalentsAtCarryingValue": "12097000", "cashAndShortTermInvestments": "12097000", "inventory": "None", "currentNetReceivables": "None", "totalNonCurrentAssets": "5210000", "propertyPlantEquipment": "None", "accumulatedDepreciationAmortizationPPE": "None", "intangibleAssets": "None", "intangibleAssetsExcludingGoodwill": "None", "goodwill": "None", "investments": "None", "longTermInvestments": "3486000", "shortTermInvestments": "46458000", "otherCurrentAssets": "1551000", "otherNonCurrentAssets": "None", "totalLiabilities": "3408000", "totalCurrentLiabilities": "3395000", "currentAccountsPayable": "1063000", "deferredRevenue": "None", "currentDebt": "None", "shortTermDebt": "None", "totalNonCurrentLiabilities": "13000", "capitalLeaseObligations": "0", "longTermDebt": "None", "currentLongTermDebt": "None", "longTermDebtNoncurrent": "None", "shortLongTermDebtTotal": "None", "otherCurrentLiabilities": "2332000", "otherNonCurrentLiabilities": "None", "totalShareholderEquity": "61908000", "treasuryStock": "None", "retainedEarnings": "-47384000", "commonStock": "None", "commonStockSharesOutstanding": "18740000"}, {"fiscalDateEnding": "2020-12-31", "reportedCurrency": "USD", "totalAssets": "4234000", "totalCurrentAssets": "4234000", "cashAndCashEquivalentsAtCarryingValue": "4070000", "cashAndShortTermInvestments": "4070000", "inventory": "None", "currentNetReceivables": "None", "totalNonCurrentAssets": "0", "propertyPlantEquipment": "None", "accumulatedDepreciationAmortizationPPE": "None", "intangibleAssets": "None", "intangibleAssetsExcludingGoodwill": "None", "goodwill": "None", "investments": "None", "longTermInvestments": "0", "shortTermInvestments": "0", "otherCurrentAssets": "164000", "otherNonCurrentAssets": "None", "totalLiabilities": "1483000", "totalCurrentLiabilities": "1459000", "currentAccountsPayable": "132000", "deferredRevenue": "None", "currentDebt": "None", "shortTermDebt": "None", "totalNonCurrentLiabilities": "24000", "capitalLeaseObligations": "None", "longTermDebt": "None", "currentLongTermDebt": "None", "longTermDebtNoncurrent": "None", "shortLongTermDebtTotal": "None", "otherCurrentLiabilities": "1327000", "otherNonCurrentLiabilities": "None", "totalShareholderEquity": "2751000", "treasuryStock": "None", "retainedEarnings": "-20319000", "commonStock": "None", "commonStockSharesOutstanding": "18740000"}, {"fiscalDateEnding": "2019-12-31", "reportedCurrency": "USD", "totalAssets": "5700000", "totalCurrentAssets": "5700000", "cashAndCashEquivalentsAtCarryingValue": "5598000", "cashAndShortTermInvestments": "5598000", "inventory": "None", "currentNetReceivables": "None", "totalNonCurrentAssets": "None", "propertyPlantEquipment": "None", "accumulatedDepreciationAmortizationPPE": "None", "intangibleAssets": "None", "intangibleAssetsExcludingGoodwill": "None", "goodwill": "None", "investments": "None", "longTermInvestments": "None", "shortTermInvestments": "None", "otherCurrentAssets": "102000", "otherNonCurrentAssets": "None", "totalLiabilities": "887000", "totalCurrentLiabilities": "159000", "currentAccountsPayable": "51000", "deferredRevenue": "None", "currentDebt": "None", "shortTermDebt": "None", "totalNonCurrentLiabilities": "728000", "capitalLeaseObligations": "None", "longTermDebt": "None", "currentLongTermDebt": "None", "longTermDebtNoncurrent": "None", "shortLongTermDebtTotal": "728000", "otherCurrentLiabilities": "108000", "otherNonCurrentLiabilities": "None", "totalShareholderEquity": "4813000", "treasuryStock": "None", "retainedEarnings": "-5801000", "commonStock": "None", "commonStockSharesOutstanding": "18740000"}], "quarterlyReports": [{"fiscalDateEnding": "2025-09-30", "reportedCurrency": "USD", "totalAssets": "67235000", "totalCurrentAssets": "64016000", "cashAndCashEquivalentsAtCarryingValue": "18003000", "cashAndShortTermInvestments": "18003000", "inventory": "None", "currentNetReceivables": "None", "totalNonCurrentAssets": "3219000", "propertyPlantEquipment": "None", "accumulatedDepreciationAmortizationPPE": "None", "intangibleAssets": "None", "intangibleAssetsExcludingGoodwill": "None", "goodwill": "None", "investments": "None", "longTermInvestments": "3219000", "shortTermInvestments": "43918000", "otherCurrentAssets": "2095000", "otherNonCurrentAssets": "None", "totalLiabilities": "6858000", "totalCurrentLiabilities": "2226000", "currentAccountsPayable": "2226000", "deferredRevenue": "None", "currentDebt": "None", "shortTermDebt": "None", "totalNonCurrentLiabilities": "4632000", "capitalLeaseObligations": "None", "longTermDebt": "None", "currentLongTermDebt": "None", "longTermDebtNoncurrent": "None", "shortLongTermDebtTotal": "None", "otherCurrentLiabilities": "183000", "otherNonCurrentLiabilities": "None", "totalShareholderEquity": "60377000", "treasuryStock": "None", "retainedEarnings": "-232240000", "commonStock": "None", "commonStockSharesOutstanding": "30276230"}, {"fiscalDateEnding": "2025-06-30", "reportedCurrency": "USD", "totalAssets": "75825000", "totalCurrentAssets": "67524000", "cashAndCashEquivalentsAtCarryingValue": "18220000", "cashAndShortTermInvestments": "18220000", "inventory": "None", "currentNetReceivables": "2700000", "totalNonCurrentAssets": "8301000", "propertyPlantEquipment": "None", "accumulatedDepreciationAmortizationPPE": "None", "intangibleAssets": "None", "intangibleAssetsExcludingGoodwill": "None", "goodwill": "None", "investments": "None", "longTermInvestments": "8301000", "shortTermInvestments": "44696000", "otherCurrentAssets": "1908000", "otherNonCurrentAssets": "None", "totalLiabilities": "6983000", "totalCurrentLiabilities": "2113000", "currentAccountsPayable": "2113000", "deferredRevenue": "None", "currentDebt": "None", "shortTermDebt": "None", "totalNonCurrentLiabilities": "4870000", "capitalLeaseObligations": "None", "longTermDebt": "None", "currentLongTermDebt": "None", "longTermDebtNoncurrent": "None", "shortLongTermDebtTotal": "None", "otherCurrentLiabilities": "717000", "otherNonCurrentLiabilities": "None", "totalShareholderEquity": "68842000", "treasuryStock": "None", "retainedEarnings": "-222887000", "commonStock": "None", "commonStockSharesOutstanding": "30172328"}, {"fiscalDateEnding": "2025-03-31", "reportedCurrency": "USD", "totalAssets": "81343000", "totalCurrentAssets": "69559000", "cashAndCashEquivalentsAtCarryingValue": "19985000", "cashAndShortTermInvestments": "19985000", "inventory": "None", "currentNetReceivables": "300000", "totalNonCurrentAssets": "11784000", "propertyPlantEquipment": "None", "accumulatedDepreciationAmortizationPPE": "None", "intangibleAssets": "None", "intangibleAssetsExcludingGoodwill": "None", "goodwill": "None", "investments": "None", "longTermInvestments": "11480000", "shortTermInvestments": "47075000", "otherCurrentAssets": "2499000", "otherNonCurrentAssets": "None", "totalLiabilities": "8014000", "totalCurrentLiabilities": "8014000", "currentAccountsPayable": "3073000", "deferredRevenue": "None", "currentDebt": "None", "shortTermDebt": "None", "totalNonCurrentLiabilities": "0", "capitalLeaseObligations": "None", "longTermDebt": "None", "currentLongTermDebt": "None", "longTermDebtNoncurrent": "None", "shortLongTermDebtTotal": "None", "otherCurrentLiabilities": "4941000", "otherNonCurrentLiabilities": "None", "totalShareholderEquity": "73329000", "treasuryStock": "None", "retainedEarnings": "-216425000", "commonStock": "None", "commonStockSharesOutstanding": "30054000"}, {"fiscalDateEnding": "2024-12-31", "reportedCurrency": "USD", "totalAssets": "92087000", "totalCurrentAssets": "86262000", "cashAndCashEquivalentsAtCarryingValue": "21351000", "cashAndShortTermInvestments": "21351000", "inventory": "None", "currentNetReceivables": "300000", "totalNonCurrentAssets": "5825000", "propertyPlantEquipment": "None", "accumulatedDepreciationAmortizationPPE": "None", "intangibleAssets": "None", "intangibleAssetsExcludingGoodwill": "None", "goodwill": "None", "investments": "None", "longTermInvestments": "5021000", "shortTermInvestments": "62267000", "otherCurrentAssets": "2344000", "otherNonCurrentAssets": "None", "totalLiabilities": "10238000", "totalCurrentLiabilities": "10238000", "currentAccountsPayable": "3317000", "deferredRevenue": "None", "currentDebt": "None", "shortTermDebt": "None", "totalNonCurrentLiabilities": "0", "capitalLeaseObligations": "None", "longTermDebt": "None", "currentLongTermDebt": "None", "longTermDebtNoncurrent": "None", "shortLongTermDebtTotal": "None", "otherCurrentLiabilities": "6921000", "otherNonCurrentLiabilities": "None", "totalShareholderEquity": "81849000", "treasuryStock": "None", "retainedEarnings": "-205776000", "commonStock": "None", "commonStockSharesOutstanding": "29883000"}, {"fiscalDateEnding": "2024-09-30", "reportedCurrency": "USD", "totalAssets": "97689000", "totalCurrentAssets": "97689000", "cashAndCashEquivalentsAtCarryingValue": "33504000", "cashAndShortTermInvestments": "33504000", "inventory": "None", "currentNetReceivables": "1000000", "totalNonCurrentAssets": "0", "propertyPlantEquipment": "None", "accumulatedDepreciationAmortizationPPE": "None", "intangibleAssets": "None", "intangibleAssetsExcludingGoodwill": "None", "goodwill": "None", "investments": "None", "longTermInvestments": "0", "shortTermInvestments": "59922000", "otherCurrentAssets": "3263000", "otherNonCurrentAssets": "None", "totalLiabilities": "10017000", "totalCurrentLiabilities": "10017000", "currentAccountsPayable": "1711000", "deferredRevenue": "None", "currentDebt": "None", "shortTermDebt": "None", "totalNonCurrentLiabilities": "0", "capitalLeaseObligations": "None", "longTermDebt": "None", "currentLongTermDebt": "None", "longTermDebtNoncurrent": "None", "shortLongTermDebtTotal": "None", "otherCurrentLiabilities": "8306000", "otherNonCurrentLiabilities": "None", "totalShareholderEquity": "87672000", "treasuryStock": "None", "retainedEarnings": "-198254000", "commonStock": "None", "commonStockSharesOutstanding": "29841000"}, {"fiscalDateEnding": "2024-06-30", "reportedCurrency": "USD", "totalAssets": "108481000", "totalCurrentAssets": "107438000", "cashAndCashEquivalentsAtCarryingValue": "26769000", "cashAndShortTermInvestments": "26769000", "inventory": "None", "currentNetReceivables": "300000", "totalNonCurrentAssets": "1043000", "propertyPlantEquipment": "None", "accumulatedDepreciationAmortizationPPE": "None", "intangibleAssets": "None", "intangibleAssetsExcludingGoodwill": "None", "goodwill": "None", "investments": "None", "longTermInvestments": "0", "shortTermInvestments": "77771000", "otherCurrentAssets": "2598000", "otherNonCurrentAssets": "None", "totalLiabilities": "10127000", "totalCurrentLiabilities": "10127000", "currentAccountsPayable": "1885000", "deferredRevenue": "None", "currentDebt": "None", "shortTermDebt": "None", "totalNonCurrentLiabilities": "8242000", "capitalLeaseObligations": "None", "longTermDebt": "None", "currentLongTermDebt": "None", "longTermDebtNoncurrent": "None", "shortLongTermDebtTotal": "None", "otherCurrentLiabilities": "8242000", "otherNonCurrentLiabilities": "None", "totalShareholderEquity": "98354000", "treasuryStock": "None", "retainedEarnings": "-185507000", "commonStock": "None", "commonStockSharesOutstanding": "29825000"}, {"fiscalDateEnding": "2024-03-31", "reportedCurrency": "USD", "totalAssets": "121260000", "totalCurrentAssets": "116313000", "cashAndCashEquivalentsAtCarryingValue": "24693000", "cashAndShortTermInvestments": "24693000", "inventory": "None", "currentNetReceivables": "500000", "totalNonCurrentAssets": "4947000", "propertyPlantEquipment": "None", "accumulatedDepreciationAmortizationPPE": "None", "intangibleAssets": "None", "intangibleAssetsExcludingGoodwill": "None", "goodwill": "None", "investments": "None", "longTermInvestments": "3904000", "shortTermInvestments": "89517000", "otherCurrentAssets": "2103000", "otherNonCurrentAssets": "None", "totalLiabilities": "10663000", "totalCurrentLiabilities": "10663000", "currentAccountsPayable": "2433000", "deferredRevenue": "None", "currentDebt": "None", "shortTermDebt": "None", "totalNonCurrentLiabilities": "8230000", "capitalLeaseObligations": "None", "longTermDebt": "None", "currentLongTermDebt": "None", "longTermDebtNoncurrent": "None", "shortLongTermDebtTotal": "None", "otherCurrentLiabilities": "8230000", "otherNonCurrentLiabilities": "None", "totalShareholderEquity": "110597000", "treasuryStock": "None", "retainedEarnings": "-171072000", "commonStock": "None", "commonStockSharesOutstanding": "29763000"}, {"fiscalDateEnding": "2023-12-31", "reportedCurrency": "USD", "totalAssets": "138744000", "totalCurrentAssets": "110507000", "cashAndCashEquivalentsAtCarryingValue": "15647000", "cashAndShortTermInvestments": "15647000", "inventory": "None", "currentNetReceivables": "1400000", "totalNonCurrentAssets": "28237000", "propertyPlantEquipment": "None", "accumulatedDepreciationAmortizationPPE": "None", "intangibleAssets": "None", "intangibleAssetsExcludingGoodwill": "None", "goodwill": "None", "investments": "None", "longTermInvestments": "27194000", "shortTermInvestments": "91648000", "otherCurrentAssets": "1812000", "otherNonCurrentAssets": "None", "totalLiabilities": "14043000", "totalCurrentLiabilities": "14043000", "currentAccountsPayable": "2676000", "deferredRevenue": "None", "currentDebt": "None", "shortTermDebt": "None", "totalNonCurrentLiabilities": "0", "capitalLeaseObligations": "0", "longTermDebt": "None", "currentLongTermDebt": "None", "longTermDebtNoncurrent": "None", "shortLongTermDebtTotal": "None", "otherCurrentLiabilities": "11367000", "otherNonCurrentLiabilities": "None", "totalShareholderEquity": "124701000", "treasuryStock": "None", "retainedEarnings": "-154455000", "commonStock": "None", "commonStockSharesOutstanding": "29735000"}, {"fiscalDateEnding": "2023-09-30", "reportedCurrency": "USD", "totalAssets": "153808000", "totalCurrentAssets": "126409000", "cashAndCashEquivalentsAtCarryingValue": "32616000", "cashAndShortTermInvestments": "32616000", "inventory": "None", "currentNetReceivables": "None", "totalNonCurrentAssets": "27399000", "propertyPlantEquipment": "None", "accumulatedDepreciationAmortizationPPE": "None", "intangibleAssets": "None", "intangibleAssetsExcludingGoodwill": "None", "goodwill": "None", "investments": "None", "longTermInvestments": "26356000", "shortTermInvestments": "91202000", "otherCurrentAssets": "2591000", "otherNonCurrentAssets": "None", "totalLiabilities": "14839000", "totalCurrentLiabilities": "14839000", "currentAccountsPayable": "4877000", "deferredRevenue": "None", "currentDebt": "None", "shortTermDebt": "None", "totalNonCurrentLiabilities": "0", "capitalLeaseObligations": "0", "longTermDebt": "None", "currentLongTermDebt": "None", "longTermDebtNoncurrent": "None", "shortLongTermDebtTotal": "None", "otherCurrentLiabilities": "9962000", "otherNonCurrentLiabilities": "None", "totalShareholderEquity": "138969000", "treasuryStock": "None", "retainedEarnings": "-137557000", "commonStock": "None", "commonStockSharesOutstanding": "25645000"}, {"fiscalDateEnding": "2023-06-30", "reportedCurrency": "USD", "totalAssets": "98926000", "totalCurrentAssets": "98206000", "cashAndCashEquivalentsAtCarryingValue": "40812000", "cashAndShortTermInvestments": "40812000", "inventory": "None", "currentNetReceivables": "None", "totalNonCurrentAssets": "720000", "propertyPlantEquipment": "None", "accumulatedDepreciationAmortizationPPE": "None", "intangibleAssets": "None", "intangibleAssetsExcludingGoodwill": "None", "goodwill": "None", "investments": "None", "longTermInvestments": "0", "shortTermInvestments": "54446000", "otherCurrentAssets": "2948000", "otherNonCurrentAssets": "None", "totalLiabilities": "11162000", "totalCurrentLiabilities": "11161000", "currentAccountsPayable": "3131000", "deferredRevenue": "None", "currentDebt": "None", "shortTermDebt": "13000", "totalNonCurrentLiabilities": "1000", "capitalLeaseObligations": "13000", "longTermDebt": "None", "currentLongTermDebt": "None", "longTermDebtNoncurrent": "None", "shortLongTermDebtTotal": "13000", "otherCurrentLiabilities": "8017000", "otherNonCurrentLiabilities": "1000", "totalShareholderEquity": "87764000", "treasuryStock": "None", "retainedEarnings": "-120850000", "commonStock": "None", "commonStockSharesOutstanding": "19497000"}, {"fiscalDateEnding": "2023-03-31", "reportedCurrency": "USD", "totalAssets": "91084000", "totalCurrentAssets": "90316000", "cashAndCashEquivalentsAtCarryingValue": "26709000", "cashAndShortTermInvestments": "26709000", "inventory": "None", "currentNetReceivables": "None", "totalNonCurrentAssets": "768000", "propertyPlantEquipment": "None", "accumulatedDepreciationAmortizationPPE": "None", "intangibleAssets": "None", "intangibleAssetsExcludingGoodwill": "None", "goodwill": "None", "investments": "None", "longTermInvestments": "0", "shortTermInvestments": "61806000", "otherCurrentAssets": "1801000", "otherNonCurrentAssets": "None", "totalLiabilities": "8567000", "totalCurrentLiabilities": "8566000", "currentAccountsPayable": "3545000", "deferredRevenue": "None", "currentDebt": "None", "shortTermDebt": "34000", "totalNonCurrentLiabilities": "1000", "capitalLeaseObligations": "34000", "longTermDebt": "None", "currentLongTermDebt": "None", "longTermDebtNoncurrent": "None", "shortLongTermDebtTotal": "34000", "otherCurrentLiabilities": "4987000", "otherNonCurrentLiabilities": "1000", "totalShareholderEquity": "82517000", "treasuryStock": "None", "retainedEarnings": "-105046000", "commonStock": "None", "commonStockSharesOutstanding": "19386000"}, {"fiscalDateEnding": "2022-12-31", "reportedCurrency": "USD", "totalAssets": "102560000", "totalCurrentAssets": "98621000", "cashAndCashEquivalentsAtCarryingValue": "27219000", "cashAndShortTermInvestments": "27219000", "inventory": "None", "currentNetReceivables": "None", "totalNonCurrentAssets": "3939000", "propertyPlantEquipment": "None", "accumulatedDepreciationAmortizationPPE": "None", "intangibleAssets": "None", "intangibleAssetsExcludingGoodwill": "None", "goodwill": "None", "investments": "None", "longTermInvestments": "3219000", "shortTermInvestments": "68840000", "otherCurrentAssets": "2562000", "otherNonCurrentAssets": "None", "totalLiabilities": "7188000", "totalCurrentLiabilities": "7186000", "currentAccountsPayable": "2122000", "deferredRevenue": "None", "currentDebt": "None", "shortTermDebt": "53000", "totalNonCurrentLiabilities": "2000", "capitalLeaseObligations": "53000", "longTermDebt": "None", "currentLongTermDebt": "None", "longTermDebtNoncurrent": "None", "shortLongTermDebtTotal": "53000", "otherCurrentLiabilities": "5011000", "otherNonCurrentLiabilities": "2000", "totalShareholderEquity": "95372000", "treasuryStock": "None", "retainedEarnings": "-89723000", "commonStock": "None", "commonStockSharesOutstanding": "19403000"}, {"fiscalDateEnding": "2022-09-30", "reportedCurrency": "USD", "totalAssets": "110008000", "totalCurrentAssets": "107296000", "cashAndCashEquivalentsAtCarryingValue": "28802000", "cashAndShortTermInvestments": "28802000", "inventory": "None", "currentNetReceivables": "None", "totalNonCurrentAssets": "2712000", "propertyPlantEquipment": "None", "accumulatedDepreciationAmortizationPPE": "None", "intangibleAssets": "None", "intangibleAssetsExcludingGoodwill": "None", "goodwill": "None", "investments": "None", "longTermInvestments": "1992000", "shortTermInvestments": "75580000", "otherCurrentAssets": "2914000", "otherNonCurrentAssets": "None", "totalLiabilities": "4435000", "totalCurrentLiabilities": "4432000", "currentAccountsPayable": "1440000", "deferredRevenue": "None", "currentDebt": "None", "shortTermDebt": "73000", "totalNonCurrentLiabilities": "3000", "capitalLeaseObligations": "73000", "longTermDebt": "None", "currentLongTermDebt": "None", "longTermDebtNoncurrent": "None", "shortLongTermDebtTotal": "73000", "otherCurrentLiabilities": "2919000", "otherNonCurrentLiabilities": "3000", "totalShareholderEquity": "105573000", "treasuryStock": "None", "retainedEarnings": "-77881000", "commonStock": "None", "commonStockSharesOutstanding": "19347000"}, {"fiscalDateEnding": "2022-06-30", "reportedCurrency": "USD", "totalAssets": "120016000", "totalCurrentAssets": "116877000", "cashAndCashEquivalentsAtCarryingValue": "40616000", "cashAndShortTermInvestments": "40616000", "inventory": "None", "currentNetReceivables": "None", "totalNonCurrentAssets": "3139000", "propertyPlantEquipment": "None", "accumulatedDepreciationAmortizationPPE": "None", "intangibleAssets": "None", "intangibleAssetsExcludingGoodwill": "None", "goodwill": "None", "investments": "None", "longTermInvestments": "2419000", "shortTermInvestments": "72773000", "otherCurrentAssets": "3488000", "otherNonCurrentAssets": "None", "totalLiabilities": "4153000", "totalCurrentLiabilities": "4149000", "currentAccountsPayable": "1612000", "deferredRevenue": "None", "currentDebt": "None", "shortTermDebt": "13000", "totalNonCurrentLiabilities": "4000", "capitalLeaseObligations": "13000", "longTermDebt": "None", "currentLongTermDebt": "None", "longTermDebtNoncurrent": "None", "shortLongTermDebtTotal": "13000", "otherCurrentLiabilities": "2524000", "otherNonCurrentLiabilities": "4000", "totalShareholderEquity": "115863000", "treasuryStock": "None", "retainedEarnings": "-66542000", "commonStock": "None", "commonStockSharesOutstanding": "19258000"}, {"fiscalDateEnding": "2022-03-31", "reportedCurrency": "USD", "totalAssets": "120503000", "totalCurrentAssets": "119783000", "cashAndCashEquivalentsAtCarryingValue": "82519000", "cashAndShortTermInvestments": "82519000", "inventory": "None", "currentNetReceivables": "None", "totalNonCurrentAssets": "720000", "propertyPlantEquipment": "None", "accumulatedDepreciationAmortizationPPE": "None", "intangibleAssets": "None", "intangibleAssetsExcludingGoodwill": "None", "goodwill": "None", "investments": "None", "longTermInvestments": "0", "shortTermInvestments": "35835000", "otherCurrentAssets": "1429000", "otherNonCurrentAssets": "None", "totalLiabilities": "5093000", "totalCurrentLiabilities": "5087000", "currentAccountsPayable": "2609000", "deferredRevenue": "None", "currentDebt": "None", "shortTermDebt": "32000", "totalNonCurrentLiabilities": "6000", "capitalLeaseObligations": "32000", "longTermDebt": "None", "currentLongTermDebt": "None", "longTermDebtNoncurrent": "None", "shortLongTermDebtTotal": "32000", "otherCurrentLiabilities": "2446000", "otherNonCurrentLiabilities": "None", "totalShareholderEquity": "115410000", "treasuryStock": "None", "retainedEarnings": "-56422000", "commonStock": "-120503000", "commonStockSharesOutstanding": "18999000"}, {"fiscalDateEnding": "2021-12-31", "reportedCurrency": "USD", "totalAssets": "65316000", "totalCurrentAssets": "60106000", "cashAndCashEquivalentsAtCarryingValue": "12097000", "cashAndShortTermInvestments": "12097000", "inventory": "None", "currentNetReceivables": "None", "totalNonCurrentAssets": "5210000", "propertyPlantEquipment": "None", "accumulatedDepreciationAmortizationPPE": "None", "intangibleAssets": "None", "intangibleAssetsExcludingGoodwill": "None", "goodwill": "None", "investments": "None", "longTermInvestments": "3486000", "shortTermInvestments": "46458000", "otherCurrentAssets": "1551000", "otherNonCurrentAssets": "None", "totalLiabilities": "3408000", "totalCurrentLiabilities": "3395000", "currentAccountsPayable": "1063000", "deferredRevenue": "None", "currentDebt": "None", "shortTermDebt": "None", "totalNonCurrentLiabilities": "13000", "capitalLeaseObligations": "None", "longTermDebt": "None", "currentLongTermDebt": "None", "longTermDebtNoncurrent": "None", "shortLongTermDebtTotal": "None", "otherCurrentLiabilities": "2332000", "otherNonCurrentLiabilities": "None", "totalShareholderEquity": "61908000", "treasuryStock": "None", "retainedEarnings": "-47384000", "commonStock": "None", "commonStockSharesOutstanding": "18140000"}, {"fiscalDateEnding": "2021-09-30", "reportedCurrency": "USD", "totalAssets": "None", "totalCurrentAssets": "None", "cashAndCashEquivalentsAtCarryingValue": "None", "cashAndShortTermInvestments": "None", "inventory": "None", "currentNetReceivables": "None", "totalNonCurrentAssets": "None", "propertyPlantEquipment": "None", "accumulatedDepreciationAmortizationPPE": "None", "intangibleAssets": "None", "intangibleAssetsExcludingGoodwill": "None", "goodwill": "None", "investments": "None", "longTermInvestments": "None", "shortTermInvestments": "None", "otherCurrentAssets": "None", "otherNonCurrentAssets": "None", "totalLiabilities": "None", "totalCurrentLiabilities": "None", "currentAccountsPayable": "None", "deferredRevenue": "None", "currentDebt": "None", "shortTermDebt": "None", "totalNonCurrentLiabilities": "None", "capitalLeaseObligations": "None", "longTermDebt": "None", "currentLongTermDebt": "None", "longTermDebtNoncurrent": "None", "shortLongTermDebtTotal": "None", "otherCurrentLiabilities": "None", "otherNonCurrentLiabilities": "None", "totalShareholderEquity": "None", "treasuryStock": "None", "retainedEarnings": "None", "commonStock": "None", "commonStockSharesOutstanding": "14048000"}, {"fiscalDateEnding": "2021-06-30", "reportedCurrency": "USD", "totalAssets": "None", "totalCurrentAssets": "None", "cashAndCashEquivalentsAtCarryingValue": "None", "cashAndShortTermInvestments": "None", "inventory": "None", "currentNetReceivables": "None", "totalNonCurrentAssets": "None", "propertyPlantEquipment": "None", "accumulatedDepreciationAmortizationPPE": "None", "intangibleAssets": "None", "intangibleAssetsExcludingGoodwill": "None", "goodwill": "None", "investments": "None", "longTermInvestments": "None", "shortTermInvestments": "None", "otherCurrentAssets": "None", "otherNonCurrentAssets": "None", "totalLiabilities": "None", "totalCurrentLiabilities": "None", "currentAccountsPayable": "None", "deferredRevenue": "None", "currentDebt": "None", "shortTermDebt": "None", "totalNonCurrentLiabilities": "None", "capitalLeaseObligations": "None", "longTermDebt": "None", "currentLongTermDebt": "None", "longTermDebtNoncurrent": "None", "shortLongTermDebtTotal": "None", "otherCurrentLiabilities": "None", "otherNonCurrentLiabilities": "None", "totalShareholderEquity": "None", "treasuryStock": "None", "retainedEarnings": "None", "commonStock": "None", "commonStockSharesOutstanding": "14048000"}, {"fiscalDateEnding": "2021-03-31", "reportedCurrency": "USD", "totalAssets": "None", "totalCurrentAssets": "4070000", "cashAndCashEquivalentsAtCarryingValue": "-4070000", "cashAndShortTermInvestments": "-4070000", "inventory": "None", "currentNetReceivables": "None", "totalNonCurrentAssets": "-4070000", "propertyPlantEquipment": "None", "accumulatedDepreciationAmortizationPPE": "None", "intangibleAssets": "None", "intangibleAssetsExcludingGoodwill": "None", "goodwill": "None", "investments": "None", "longTermInvestments": "None", "shortTermInvestments": "8140000", "otherCurrentAssets": "None", "otherNonCurrentAssets": "None", "totalLiabilities": "None", "totalCurrentLiabilities": "None", "currentAccountsPayable": "None", "deferredRevenue": "None", "currentDebt": "None", "shortTermDebt": "None", "totalNonCurrentLiabilities": "None", "capitalLeaseObligations": "None", "longTermDebt": "None", "currentLongTermDebt": "None", "longTermDebtNoncurrent": "None", "shortLongTermDebtTotal": "None", "otherCurrentLiabilities": "None", "otherNonCurrentLiabilities": "None", "totalShareholderEquity": "2751000", "treasuryStock": "None", "retainedEarnings": "None", "commonStock": "None", "commonStockSharesOutstanding": "14048000"}]}