{"Symbol": "ALK", "AssetType": "Common Stock", "Name": "Alaska Air Group Inc", "Description": "Alaska Air Group is an airline holding company based in SeaTac, Washington, United States.", "CIK": "766421", "Exchange": "NYSE", "Currency": "USD", "Country": "USA", "Sector": "INDUSTRIALS", "Industry": "AIRLINES", "Address": "19300 INTERNATIONAL BOULEVARD, SEATTLE, WA, UNITED STATES, 98188", "OfficialSite": "https://www.alaskaair.com", "FiscalYearEnd": "December", "LatestQuarter": "2025-12-31", "MarketCapitalization": "6336233000", "EBITDA": "1271000000", "PERatio": "66.59", "PEGRatio": "1.3", "BookValue": "35.64", "DividendPerShare": "None", "DividendYield": "None", "EPS": "0.83", "RevenuePerShareTTM": "120.5", "ProfitMargin": "0.007", "OperatingMarginTTM": "0.0319", "ReturnOnAssetsTTM": "0.0173", "ReturnOnEquityTTM": "0.0236", "RevenueTTM": "14239000000", "GrossProfitTTM": "3063000000", "DilutedEPSTTM": "0.83", "QuarterlyEarningsGrowthYOY": "-0.683", "QuarterlyRevenueGrowthYOY": "0.028", "AnalystTargetPrice": "70.8", "AnalystRatingStrongBuy": "4", "AnalystRatingBuy": "11", "AnalystRatingHold": "0", "AnalystRatingSell": "0", "AnalystRatingStrongSell": "0", "TrailingPE": "66.59", "ForwardPE": "9.8", "PriceToSalesRatioTTM": "0.445", "PriceToBookRatio": "1.539", "EVToRevenue": "0.78", "EVToEBITDA": "9.44", "Beta": "1.172", "52WeekHigh": "78.08", "52WeekLow": "37.63", "50DayMovingAverage": "51.64", "200DayMovingAverage": "50.98", "SharesOutstanding": "114641000", "SharesFloat": "114014000", "PercentInsiders": "0.559", "PercentInstitutions": "95.332", "DividendDate": "2015-09-01", "ExDividendDate": "2020-02-14"}